MainPlaySoft/__init__.py
MainPlaySoft/__main__.py
MainPlaySoft/_module_info.py
MainPlaySoft/core.py
MainPlaySoft/depends.py
MainPlaySoft/dir.py
MainPlaySoft/lang.py
mainplaysoft-0.0.2.dist-info/METADATA
mainplaysoft-0.0.2.dist-info/WHEEL
mainplaysoft-0.0.2.dist-info/RECORD
